ifly_atp_sdk/__init__.py
ifly_atp_sdk/client.py
ifly_atp_sdk/config.py
ifly_atp_sdk/error.py
ifly_atp_sdk/huggingface/datasets.py
ifly_atp_sdk/huggingface/pipelines.py
ifly_atp_sdk/pretrain/__init__.py
ifly_atp_sdk/pretrain/av2vec/__init__.py
ifly_atp_sdk/pretrain/av2vec/av2vec.py
ifly_atp_sdk/pretrain/av2vec/data.py
ifly_atp_sdk/pretrain/voice2vec/__init__.py
ifly_atp_sdk/pretrain/voice2vec/data.py
ifly_atp_sdk/pretrain/voice2vec/main.py
ifly_atp_sdk/pretrain/voice2vec/voice2vec.py
ifly_atp_sdk/utils/aipass_client.py
ifly_atp_sdk/utils/exception.py
ifly_atp_sdk/utils/log.py
ifly_atp_sdk/utils/ne_utils.py
ifly_atp_sdk-0.1.1.dist-info/WHEEL
ifly_atp_sdk-0.1.1.dist-info/METADATA
ifly_atp_sdk-0.1.1.dist-info/RECORD
